[
  {
    "id": 230,
    "point_id": 1,
    "title": "PayPayクレジット紹介プログラム",
    "period_text": "2026/3/3（火）〜 3/30（月）",
    "reward_rate_text": "500ポイント（最大10人、合計5,000ポイント）",
    "entry_required": 1,
    "target_stores": null,
    "detail_url": "https://paypay.ne.jp/event/referral-20260303/",
    "source_list_url": "https://paypay.ne.jp/event/",
    "is_show": 1,
    "service_name": "PayPay"
  },
  {
    "id": 231,
    "point_id": 1,
    "title": "スギ薬局で最大全額戻ってくるPayPayスクラッチくじ",
    "period_text": "2026年3月3日（火）0:00～2026年3月29日（日）23:59",
    "reward_rate_text": "2回に1回の確率で決済金額の100％、5％、または0.5％いずれかが当たる（付与上限100,000ポイント／回および期間）",
    "entry_required": 0,
    "target_stores": "スギ薬局、スギドラッグ、ドラッグスギ、ジャパン",
    "detail_url": "https://paypay.ne.jp/event/sugi-20260303/",
    "source_list_url": "https://paypay.ne.jp/event/",
    "is_show": 1,
    "service_name": "PayPay"
  },
  {
    "id": 232,
    "point_id": 1,
    "title": "カインズで最大全額戻ってくるPayPayスクラッチくじ",
    "period_text": "2026年3月11日（水）6:00～2026年3月24日（火）23:59",
    "reward_rate_text": "1等：100％、2等：5％、3等：0.5％（付与上限：100,000ポイント／回・期間）",
    "entry_required": 0,
    "target_stores": "全国のカインズ店舗",
    "detail_url": "https://paypay.ne.jp/event/cainz-20260311/",
    "source_list_url": "https://paypay.ne.jp/event/",
    "is_show": 1,
    "service_name": "PayPay"
  },
  {
    "id": 233,
    "point_id": 1,
    "title": "PayPayスクラッチくじ",
    "period_text": "2026/3/3（火）〜3/30（月）",
    "reward_rate_text": "くじで当たるとPayPayポイント付与（付与上限：10万ポイント／回および期間）",
    "entry_required": 1,
    "target_stores": null,
    "detail_url": "https://paypay.ne.jp/event/matsuri202603-paypay-scratch/",
    "source_list_url": "https://paypay.ne.jp/event/",
    "is_show": 1,
    "service_name": "PayPay"
  },
  {
    "id": 234,
    "point_id": 1,
    "title": "＜12〜18歳の方＞PayPay残高へのチャージ＆お支払いでPayPayポイントが最大2％上乗せでもらえるキャンペーン",
    "period_text": "2026/3/3（火）〜 終了日未定",
    "reward_rate_text": "最大2％上乗せ",
    "entry_required": 0,
    "target_stores": null,
    "detail_url": "https://paypay.ne.jp/event/charge-pay-youth-20260303/",
    "source_list_url": "https://paypay.ne.jp/event/",
    "is_show": 1,
    "service_name": "PayPay"
  },
  {
    "id": 235,
    "point_id": 1,
    "title": "大賀BibicaアプリからPayPayで支払うと最大15％戻ってくるキャンペーン",
    "period_text": "2026年3月1日（日）8:00～2026年4月30日（木）23:59",
    "reward_rate_text": "最大15％付与 (上限500ポイント／回および期間)",
    "entry_required": 0,
    "target_stores": "全国の大賀薬局店舗",
    "detail_url": "https://paypay.ne.jp/event/ohga-20260301/",
    "source_list_url": "https://paypay.ne.jp/event/",
    "is_show": 1,
    "service_name": "PayPay"
  },
  {
    "id": 236,
    "point_id": 1,
    "title": "PayPay U18応援プロジェクト",
    "period_text": "3月24日開始予定（終了日未定）",
    "reward_rate_text": "最大2％上乗せ",
    "entry_required": 0,
    "target_stores": null,
    "detail_url": "https://paypay.ne.jp/event/youth-20260303/",
    "source_list_url": "https://paypay.ne.jp/event/",
    "is_show": 1,
    "service_name": "PayPay"
  },
  {
    "id": 237,
    "point_id": 1,
    "title": "本人確認で100ポイントもらえるキャンペーン",
    "period_text": "2026/2/5（木）～5/31（日）",
    "reward_rate_text": "100ポイント",
    "entry_required": 0,
    "target_stores": null,
    "detail_url": "https://paypay.ne.jp/event/ekyc-20260129/",
    "source_list_url": "https://paypay.ne.jp/event/",
    "is_show": 1,
    "service_name": "PayPay"
  },
  {
    "id": 238,
    "point_id": 1,
    "title": "銀行集合キャンペーン",
    "period_text": "2026年2月2日（月）00:00 〜 3月22日（日）23:59 まで",
    "reward_rate_text": "最大500ポイント",
    "entry_required": 1,
    "target_stores": "あいち銀行、池田泉州銀行、岩手銀行、北日本銀行、紀陽銀行、京都銀行、清水銀行、滋賀銀行、セブン銀行、千葉興業銀行、東北銀行、トマト銀行、南都銀行、西日本シティ銀行、百十四銀行、福島銀行、北洋銀行、宮崎太陽銀行、山梨中央銀行、横浜銀行、JAバンク京都（JA京都、JA京都市、JA京都中央、JA京都にのくに、JA京都やましろ）",
    "detail_url": "https://paypay.ne.jp/event/bank-20260202/",
    "source_list_url": "https://paypay.ne.jp/event/",
    "is_show": 1,
    "service_name": "PayPay"
  },
  {
    "id": 239,
    "point_id": 1,
    "title": "「対象店舗でカルテHD商品購入で最大10％戻ってくる」キャンペーン",
    "period_text": "2026/1/25（日）〜3/31（火）",
    "reward_rate_text": "最大10％",
    "entry_required": 1,
    "target_stores": "アインズ＆トルペ、アインズ、ウエルシア薬局、ハックドラッグ、金光薬品、とをしや薬局、ダックス、ハッピー・ドラッグ、よどやドラッグ、マルエドラッグ、コクミン、ふく薬品、スーパードラッグひまわり、シミズ、ハックエクスプレス、Ｂ.Ｂ.ＯＮ、大賀薬局、アイココチ、カワチ薬品、ドラッグストアクラモチ、CAWACHI、カワチファーマシー、キリン堂、クスリのアオキ、サンキュードラッグ、サンドラッグ、ドラッグトップス、スギドラッグ、スギ薬局、ドラッグスギ、ウォンツ、杏林堂薬局、くすりの福太郎、くすりのレデイ、ツルハドラッグ、ドラッグイレブン、ドラッグストアウェルネス、メディコ21、B&D、クスリのツルハ、インクローバー、カツマタ、トモズ、AMERICAN PHARMACY、AP by AMERICAN PHARMACY、スーパードラッグアサヒ、スーパーシティアサヒ",
    "detail_url": "https://paypay.ne.jp/event/retail-kosemaruhopharma-20260125/",
    "source_list_url": "https://paypay.ne.jp/event/",
    "is_show": 1,
    "service_name": "PayPay"
  },
  {
    "id": 240,
    "point_id": 1,
    "title": "PayPay使ってギガ増量キャンペーン",
    "period_text": "2025/11/1（土）〜 終了日未定",
    "reward_rate_text": "データ容量追加",
    "entry_required": 1,
    "target_stores": null,
    "detail_url": "https://paypay.ne.jp/event/ymobile-giga-20251101/",
    "source_list_url": "https://paypay.ne.jp/event/",
    "is_show": 1,
    "service_name": "PayPay"
  },
  {
    "id": 241,
    "point_id": 1,
    "title": "ワイモバイル契約でPayPayポイントもらえるキャンペーン",
    "period_text": "2024年2月6日〜2026年3月25日終了",
    "reward_rate_text": "最大15,000円相当を付与",
    "entry_required": 1,
    "target_stores": null,
    "detail_url": "https://paypay.ne.jp/event/ymobile-20240830/",
    "source_list_url": "https://paypay.ne.jp/event/",
    "is_show": 1,
    "service_name": "PayPay"
  },
  {
    "id": 242,
    "point_id": 1,
    "title": "友だち紹介特典 - キャッシュレス決済のPayPay",
    "period_text": "2024/6/5（水）9:00〜終了日未定",
    "reward_rate_text": "紹介で300ポイント、U18応援プロジェクト対象者は追加で200ポイント（合計500ポイント）",
    "entry_required": 1,
    "target_stores": null,
    "detail_url": "https://paypay.ne.jp/event/referral/",
    "source_list_url": "https://paypay.ne.jp/event/",
    "is_show": 1,
    "service_name": "PayPay"
  },
  {
    "id": 243,
    "point_id": 1,
    "title": "1年間ずっとおこづかい増量キャンペーン！",
    "period_text": "本キャンペーンは終了日未定です。",
    "reward_rate_text": "毎月最大10％のPayPayポイント。ソフトバンク同士なら最大20％のPayPayポイント。付与上限：最大250ポイント／月、または最大500ポイント／月（ソフトバンクユーザー同士かつ送る側が「ペイトク」プラン加入）。",
    "entry_required": 1,
    "target_stores": null,
    "detail_url": "https://paypay.ne.jp/event/send-20241219/",
    "source_list_url": "https://paypay.ne.jp/event/",
    "is_show": 1,
    "service_name": "PayPay"
  },
  {
    "id": 244,
    "point_id": 1,
    "title": "ペイしてトクトクキャンペーン2",
    "period_text": null,
    "reward_rate_text": "最大付与率: 【PayPay（残高／ポイント）】基本付与分0.5％ + 条件達成特典0.5％、【PayPayクレジット】（PayPayカード紐づけの場合）基本付与分1.0％ + 条件達成特典0.5％、【PayPayクレジット】（PayPayカード ゴールド紐づけの場合）基本付与分1.0％ + 条件達成特典0.5％ + PayPayカード ゴールド特典0.5％の合算",
    "entry_required": 0,
    "target_stores": null,
    "detail_url": "https://paypay.ne.jp/event/paytoku-20240214/",
    "source_list_url": "https://paypay.ne.jp/event/",
    "is_show": 1,
    "service_name": "PayPay"
  },
  {
    "id": 245,
    "point_id": 1,
    "title": "つみたて還元プログラム",
    "period_text": "残高つみたて: 2023.9.4（月）0:00〜終了日未定、クレジットつみたて: 2023.10.16（月）0:00〜終了日未定",
    "reward_rate_text": "PayPayクレジット利用分 0.7％、PayPay残高・PayPayポイント利用分 0.5％ (付与上限700pt／月)",
    "entry_required": 0,
    "target_stores": null,
    "detail_url": "https://paypay.ne.jp/event/investment-20230904/",
    "source_list_url": "https://paypay.ne.jp/event/",
    "is_show": 1,
    "service_name": "PayPay"
  },
  {
    "id": 246,
    "point_id": 1,
    "title": "長期継続特典でPayPayポイントもらえる！",
    "period_text": "2025年8月31日（日）を持ちまして本特典は終了しました。",
    "reward_rate_text": "1,000 ポイント",
    "entry_required": 1,
    "target_stores": null,
    "detail_url": "https://paypay.ne.jp/event/choki-keizoku/",
    "source_list_url": "https://paypay.ne.jp/event/",
    "is_show": 1,
    "service_name": "PayPay"
  },
  {
    "id": 248,
    "point_id": 1,
    "title": "PayPayポイントコード",
    "period_text": null,
    "reward_rate_text": "PayPayポイント（1円から設定可能）",
    "entry_required": 0,
    "target_stores": "全国のPayPay加盟店",
    "detail_url": "https://paypay.ne.jp/biz/giftcard/",
    "source_list_url": "https://paypay.ne.jp/event/",
    "is_show": 1,
    "service_name": "PayPay"
  },
  {
    "id": 249,
    "point_id": 5,
    "title": "給与受取口座はOliveがおトクでおすすめ！",
    "period_text": null,
    "reward_rate_text": "毎月200Vポイント, 最大7,600円相当のVポイント, 最大3%還元",
    "entry_required": 1,
    "target_stores": null,
    "detail_url": "https://www.smbc.co.jp/kojin/open-account/salary_new/",
    "source_list_url": "https://www.smbc.co.jp/kojin/campaign/",
    "is_show": 1,
    "service_name": "Oliveカード"
  },
  {
    "id": 250,
    "point_id": 5,
    "title": "Vポイントアッププログラム",
    "period_text": null,
    "reward_rate_text": "最大20倍ポイント還元",
    "entry_required": 1,
    "target_stores": "コンビニ、飲食店",
    "detail_url": "https://www.smbc.co.jp/kojin/vpoint-up/",
    "source_list_url": "https://www.smbc.co.jp/kojin/campaign/",
    "is_show": 1,
    "service_name": "Oliveカード"
  },
  {
    "id": 252,
    "point_id": 5,
    "title": "Olive PUACL2026大会協賛キャンペーン",
    "period_text": "2026年3月13日 (金) 〜2026年4月30日 (木)",
    "reward_rate_text": "合計1,000名様にPUACL2026タオルまたはポケモン30周年ロゴをランダムでプレゼント",
    "entry_required": 1,
    "target_stores": null,
    "detail_url": "https://www.smbc.co.jp/kojin/olive/special/campaign/collab/PUACL202603/?aff=CP04652_i_webTCP_CT53598",
    "source_list_url": "https://www.smbc.co.jp/kojin/campaign/",
    "is_show": 1,
    "service_name": "Oliveカード"
  },
  {
    "id": 253,
    "point_id": 5,
    "title": "マネーフォワード MEとの連携キャンペーン",
    "period_text": "2026/3/2(月) ~ 2026/3/31(火)",
    "reward_rate_text": "1等 抽選で10名様に50,000円相当のVポイント、2等 抽選で25,000名様に100円相当のVポイント",
    "entry_required": 1,
    "target_stores": null,
    "detail_url": "https://www.smbc.co.jp/kojin/olive/special/campaign/moneyforward/202603?link_id=CP04696_i_webTCP_CT53552_img&utm_source=web&utm_medium=TCP&utm_campaign=CP04696_i_webTCP_CT53552_img",
    "source_list_url": "https://www.smbc.co.jp/kojin/campaign/",
    "is_show": 1,
    "service_name": "Oliveカード"
  },
  {
    "id": 254,
    "point_id": 5,
    "title": "Olive くら寿司限定キャンペーン",
    "period_text": "2026年3月9日(月) ～ 2026年5月8日(金)",
    "reward_rate_text": "くら寿司で使える2,000円分のデジタルお食事券",
    "entry_required": 1,
    "target_stores": "くら寿司",
    "detail_url": "https://www.smbc.co.jp/kojin/olive/special/campaign/collab/kurasushi202603/?link_id=CP04676_i_webTCP_CT52313_img&utm_source=web&utm_medium=TCP&utm_campaign=CP04676_i_webTCP_CT52313_img",
    "source_list_url": "https://www.smbc.co.jp/kojin/campaign/",
    "is_show": 1,
    "service_name": "Oliveカード"
  },
  {
    "id": 255,
    "point_id": 5,
    "title": "Olive x giftee限定キャンペーン",
    "period_text": "2026年3月2日(月) 〜 2026年3月31日(火)",
    "reward_rate_text": "サーティワン アイスクリーム、タリーズコーヒーなどから選べるgiftee Box Select 1,500ポイント",
    "entry_required": 1,
    "target_stores": null,
    "detail_url": "https://www.smbc.co.jp/kojin/olive/special/campaign/collab/giftee202603/?aff=CP04678_i_webTCP_CT53731_img&utm_source=web&utm_medium=TCP&utm_campaign=CP04678_i_webTCP_CT53731_img",
    "source_list_url": "https://www.smbc.co.jp/kojin/campaign/",
    "is_show": 1,
    "service_name": "Oliveカード"
  },
  {
    "id": 256,
    "point_id": 5,
    "title": "yOlive‘ —ÍŠÒŒ³ Õ zOlive‚ÌŒû ÀŽc ‚‚ð‘ ‚â‚·‚Æ A2 l‚É1 l Å‘å10–œ‰~‘Š“–‚ª“–‚½‚é I—a‹à‚¨ˆø‰z‚µƒLƒƒ“y [ƒ“",
    "period_text": "2026”N3ŒŽ2“ú(ŒŽ) `2026”N3ŒŽ31“ú(‰Î)",
    "reward_rate_text": "Å‘å10–œ‰~‘Š“–‚ÌVƒ|ƒCƒNƒg",
    "entry_required": 1,
    "target_stores": null,
    "detail_url": "https://www.smbc.co.jp/kojin/olive/special/campaign/yokin/yokin-ohikkoshi_2603/?aff=CP04738_i_webOTH_CT52683_img&utm_source=web&utm_medium=OTH&utm_campaign=CP04738_i_webOTH_CT52683_img",
    "source_list_url": "https://www.smbc.co.jp/kojin/campaign/",
    "is_show": 1,
    "service_name": "Oliveカード"
  },
  {
    "id": 257,
    "point_id": 5,
    "title": "最大5万円相当のVポイントが当たる！春のまとめ買いキャンペーン！",
    "period_text": "2026年3月2日 (月) 〜 2026年3月31日 (火)",
    "reward_rate_text": "最大50,000Vポイントが当たる (1等:50,000Vポイント、2等:2,000Vポイント、3等:100Vポイント)",
    "entry_required": 1,
    "target_stores": "国内・海外のVisa加盟店、VisaまたはiDマークのあるコンビニ、レストラン、ネットショップなど",
    "detail_url": "https://www.smbc.co.jp/kojin/olive/special/campaign/debit/2026spring/?link_id=CP04624_i_webOTH_CT51923_img&utm_source=web&utm_medium=OTH&utm_campaign=CP04624_i_webOTH_CT51923_img",
    "source_list_url": "https://www.smbc.co.jp/kojin/campaign/",
    "is_show": 1,
    "service_name": "Oliveカード"
  },
  {
    "id": 258,
    "point_id": 5,
    "title": "Olive とピザーラ限定キャンペーン",
    "period_text": "2026年2月24日(火) `2026年3月24日(火)",
    "reward_rate_text": "2,500円分クーポン",
    "entry_required": 1,
    "target_stores": "ピザーラ、ビバパエリア",
    "detail_url": "https://www.smbc.co.jp/kojin/olive/special/campaign/collab/pizza-la202602/?aff=CP04641_i_webTCP_CT51831_img&utm_source=web&utm_medium=TCP&utm_campaign=CP04641_i_webTCP_CT51831_img",
    "source_list_url": "https://www.smbc.co.jp/kojin/campaign/",
    "is_show": 1,
    "service_name": "Oliveカード"
  },
  {
    "id": 259,
    "point_id": 5,
    "title": "Olive × ロッテマリーンズ限定キャンペーン",
    "period_text": "2026年2月24日（火）〜2026年3月25日（水）",
    "reward_rate_text": "抽選でファーストピッチ権、観戦ペアチケット、スタジアム見学ツアー、サイン入りグッズなどをプレゼント。Oliveアカウント残高30,000円以上が条件。",
    "entry_required": 1,
    "target_stores": null,
    "detail_url": "https://www.smbc.co.jp/kojin/olive/special/campaign/collab/marines202602/?aff=CP04622_i_webTCP_CT51583_img&utm_source=web&utm_medium=TCP&utm_campaign=CP04622_i_webTCP_CT51583_img",
    "source_list_url": "https://www.smbc.co.jp/kojin/campaign/",
    "is_show": 1,
    "service_name": "Oliveカード"
  },
  {
    "id": 260,
    "point_id": 5,
    "title": "Olive × 松屋フーズ限定キャンペーン",
    "period_text": "2026年2月2日(月) 〜 2026年3月16日(月)",
    "reward_rate_text": "松屋ポイント2,000ポイント",
    "entry_required": 1,
    "target_stores": "松屋フーズ",
    "detail_url": "https://www.smbc.co.jp/kojin/olive/special/campaign/collab/matsuyafoods202602/?link_id=CP04582_i_webTCP_CT50605_img&utm_source=web&utm_medium=TCP&utm_campaign=CP04582_i_webTCP_CT50605_img",
    "source_list_url": "https://www.smbc.co.jp/kojin/campaign/",
    "is_show": 1,
    "service_name": "Oliveカード"
  },
  {
    "id": 261,
    "point_id": 5,
    "title": "Olive切替＆条件達成で5,000円相当プレゼントキャンペーン",
    "period_text": null,
    "reward_rate_text": "5,000円相当",
    "entry_required": 1,
    "target_stores": null,
    "detail_url": "https://pub.msg.smbc.co.jp/krt_switchcampaign2602_CP04610",
    "source_list_url": "https://www.smbc.co.jp/kojin/campaign/",
    "is_show": 1,
    "service_name": "Oliveカード"
  },
  {
    "id": 262,
    "point_id": 5,
    "title": "金利のある世界でOliveという選択 普通預金金利 最大年0.8%(税引前)相当 Vポイント上乗せキャンペーン：三井住友銀行",
    "period_text": "2026年2月2日〜3月31日",
    "reward_rate_text": "最大年0.8% (税引後年0.739%)相当",
    "entry_required": 1,
    "target_stores": null,
    "detail_url": "https://www.smbc.co.jp/kojin/olive/special/campaign/yokin/hutsu_2602/?aff=CP04599_o_mvKP_CT50434_img&utm_source=mv&utm_medium=KP&utm_campaign=CP04599_o_mvKP_CT50434_img",
    "source_list_url": "https://www.smbc.co.jp/kojin/campaign/",
    "is_show": 1,
    "service_name": "Oliveカード"
  },
  {
    "id": 263,
    "point_id": 5,
    "title": "【Oliveへお引越し応援】Olive切替・条件達成で5,000円相当のVポイントプレゼントキャンペーン",
    "period_text": "2026年2月2日 (月) 〜2026年4月30日 (木)",
    "reward_rate_text": "5,000円相当のVポイントプレゼント",
    "entry_required": 1,
    "target_stores": null,
    "detail_url": "https://www.smbc.co.jp/kojin/olive/special/campaign/switch/cp2602?link_id=CP04610_i_webOTH_CT52166_img&utm_source=web&utm_medium=OTH&utm_campaign=CP04610_i_webOTH_CT52166_img",
    "source_list_url": "https://www.smbc.co.jp/kojin/campaign/",
    "is_show": 1,
    "service_name": "Oliveカード"
  },
  {
    "id": 264,
    "point_id": 5,
    "title": "SBI証券の口座開設・クレカ積立などで最大16,600円相当のVポイントプレゼント！",
    "period_text": "2024年1月4日（木）以降",
    "reward_rate_text": "最大16,600円相当のVポイントプレゼント、クレカ積立で最大3%還元（ゴールド最大1%、プラチナプリファード最大3%）",
    "entry_required": 1,
    "target_stores": null,
    "detail_url": "https://www.smbc.co.jp/kojin/olive/special/offers/SBI-program.html?link_id=CP04278_i_webTCP_CT42536_img&utm_source=web&utm_medium=TCP&utm_campaign=CP04278_i_webTCP_CT42536_img",
    "source_list_url": "https://www.smbc.co.jp/kojin/campaign/",
    "is_show": 1,
    "service_name": "Oliveカード"
  },
  {
    "id": 265,
    "point_id": 5,
    "title": "Olive新規口座開設・利用で2万円相当プレゼント！キャンペーン",
    "period_text": null,
    "reward_rate_text": "2万円相当プレゼント, 15,000円相当のVポイント",
    "entry_required": 1,
    "target_stores": null,
    "detail_url": "https://www.smbc.co.jp/kojin/olive/special/campaign/open/cp2602?aff=CP04642_i_webOTH_CT50946_img&utm_source=web&utm_medium=OTH&utm_campaign=CP04642_i_webOTH_CT50946_img",
    "source_list_url": "https://www.smbc.co.jp/kojin/campaign/",
    "is_show": 1,
    "service_name": "Oliveカード"
  },
  {
    "id": 266,
    "point_id": 5,
    "title": "Oliveでの給与受取で1年間で最大10,000円相当もらえる！",
    "period_text": null,
    "reward_rate_text": "1年間で最大10,000円相当（毎月200円相当）",
    "entry_required": 1,
    "target_stores": null,
    "detail_url": "https://www.smbc.co.jp/kojin/olive/special/campaign/kyuyo_plan/?aff=CP04248_i_webTCP_CT42051_img&utm_source=web&utm_medium=TCP&utm_campaign=CP04248_i_webTCP_CT42051_img",
    "source_list_url": "https://www.smbc.co.jp/kojin/campaign/",
    "is_show": 1,
    "service_name": "Oliveカード"
  },
  {
    "id": 267,
    "point_id": 5,
    "title": "Olive限定！外貨預金口座開設キャンペーン",
    "period_text": "エントリー・預入期間: 2026/1/19(月) 〜 2026/4/17(金)23:59、外貨残高判定日時: 2026年6月30日(火) 15時",
    "reward_rate_text": "外貨預金残高200米ドル相当額以上でVポイント3,000円相当、外貨預金残高10,000米ドル相当額以上でVポイント50,000円相当",
    "entry_required": 1,
    "target_stores": null,
    "detail_url": "https://www.smbc.co.jp/kojin/olive/special/campaign/gaika/kouza2601?link_id=CP04294_i_webOTH_CT48463_img&utm_source=web&utm_medium=OTH&utm_campaign=CP04294_i_webOTH_CT48463_img",
    "source_list_url": "https://www.smbc.co.jp/kojin/campaign/",
    "is_show": 1,
    "service_name": "Oliveカード"
  },
  {
    "id": 268,
    "point_id": 5,
    "title": "SMBC toto Vポイントプレゼントプログラム",
    "period_text": "毎月1日～末日",
    "reward_rate_text": "抽選で3名様に10万ポイント",
    "entry_required": 0,
    "target_stores": null,
    "detail_url": "https://www.smbc.co.jp/kojin/campaign/toto/202310?aff=CP02681_i_webTCP_CT38479_img&utm_source=web&utm_medium=TCP&utm_campaign=CP02681_i_webTCP_CT38479_img",
    "source_list_url": "https://www.smbc.co.jp/kojin/campaign/",
    "is_show": 1,
    "service_name": "Oliveカード"
  },
  {
    "id": 269,
    "point_id": 5,
    "title": "Olive Infinite リリース事前キャンペーン：三井住友銀行",
    "period_text": "2025年9月30日(火) ~ 2026年4月30日(金)",
    "reward_rate_text": "33,000円相当Vポイント, 基本1.0%還元, 対象コンビニ・飲食店で最大20%還元, SBI証券クレカ積立で最大4.0%還元, 最大110,000pt",
    "entry_required": 1,
    "target_stores": null,
    "detail_url": "https://www.smbc.co.jp/kojin/olive/special/campaign/infinite/inf_pre/?link_id=CP04251_i_webTCP_CT43304_img&utm_source=web&utm_medium=TCP&utm_campaign=CP04251_i_webTCP_CT43304_img",
    "source_list_url": "https://www.smbc.co.jp/kojin/campaign/",
    "is_show": 1,
    "service_name": "Oliveカード"
  },
  {
    "id": 270,
    "point_id": 5,
    "title": "“Š MŽ©“® Ï—§ w“üŽžŽè ”—¿–³—¿ƒvƒ‰ƒ“ uSMBC‚Â‚Ý‚½‚Äƒ~ƒ‰ƒC v",
    "period_text": "2025”N1ŒŽ6“ú iŒŽ jˆÈ ~ i–ñ’è“úŠî € j",
    "reward_rate_text": "w“üŽžŽè ”—¿–³—¿",
    "entry_required": 0,
    "target_stores": null,
    "detail_url": "https://www.smbc.co.jp/kojin/special/smbctsumitate-mirai/?link_id=CP03614_i_webTCP_CT33348_txt&utm_source=web&utm_medium=TCP&utm_campaign=CP03614_i_webTCP_CT33348_txt",
    "source_list_url": "https://www.smbc.co.jp/kojin/campaign/",
    "is_show": 1,
    "service_name": "Oliveカード"
  },
  {
    "id": 271,
    "point_id": 5,
    "title": "iDeCoの移換手続きで、移換金額に応じてVポイントをプレゼント：三井住友銀行",
    "period_text": null,
    "reward_rate_text": "移換金額1万円～100万円未満で1,000円相当、100万円～500万円未満で5,000円相当、500万円～1,000万円未満で10,000円相当、1,000万円～3,000万円未満で15,000円相当、3,000万円以上で30,000円相当のVポイント",
    "entry_required": 1,
    "target_stores": null,
    "detail_url": "https://www.smbc.co.jp/kojin/special/ideco/0701ikan/?link_id=CP04040_i_webTCP_CT41440_img&utm_source=web&utm_medium=TCP&utm_campaign=CP04040_i_webTCP_CT41440_img",
    "source_list_url": "https://www.smbc.co.jp/kojin/campaign/",
    "is_show": 1,
    "service_name": "Oliveカード"
  },
  {
    "id": 273,
    "point_id": 2,
    "title": "楽天カード会員様特典",
    "period_text": null,
    "reward_rate_text": "5,000ポイント",
    "entry_required": 1,
    "target_stores": "スーパーやコンビニ",
    "detail_url": "https://www.rakuten-card.co.jp/fintech/?l-id=corp_oo_from_gnav_to_fintech_responsive",
    "source_list_url": "https://www.rakuten-card.co.jp/campaign/?l-id=corp_oo_gnav_campaign_responsive",
    "is_show": 1,
    "service_name": "楽天カード"
  },
  {
    "id": 274,
    "point_id": 2,
    "title": "新規入会＆利用でポイント進呈｜楽天カード",
    "period_text": null,
    "reward_rate_text": "新規入会＆利用で最大5,000ポイント、自動でリボ払い登録＆利用で最大5,000ポイント、キャッシング枠ご希望で最大1,000ポイント",
    "entry_required": 1,
    "target_stores": null,
    "detail_url": "https://www.rakuten-card.co.jp/campaign/rakuten_card/corp/?l-id=corp_oo_gnav_to_corp_lp_pc",
    "source_list_url": "https://www.rakuten-card.co.jp/campaign/?l-id=corp_oo_gnav_campaign_responsive",
    "is_show": 1,
    "service_name": "楽天カード"
  },
  {
    "id": 275,
    "point_id": 2,
    "title": "クレカデビューは楽天カード",
    "period_text": "常時開催",
    "reward_rate_text": "新規入会&3回利用で 5,000 ポイント（入会特典2,000ポイント、カード利用特典3,000ポイント）",
    "entry_required": 0,
    "target_stores": null,
    "detail_url": "https://www.rakuten-card.co.jp/campaign/rakuten_card/student/?l-id=corp_oo_gnav_to_genz_pc",
    "source_list_url": "https://www.rakuten-card.co.jp/campaign/?l-id=corp_oo_gnav_campaign_responsive",
    "is_show": 1,
    "service_name": "楽天カード"
  },
  {
    "id": 276,
    "point_id": 2,
    "title": "新規入会＆利用でポイント進呈｜楽天カード",
    "period_text": null,
    "reward_rate_text": "新規入会&利用で合計5,000ポイント、自動でリボ払い登録＆利用で最大5,000ポイント、キャッシング枠希望で最大1,000ポイント、通常利用で1%還元",
    "entry_required": 1,
    "target_stores": null,
    "detail_url": "https://www.rakuten-card.co.jp/campaign/rakuten_card/corp/?l-id=corp_oo_cpnbr_list_card_pc_a",
    "source_list_url": "https://www.rakuten-card.co.jp/campaign/?l-id=corp_oo_gnav_campaign_responsive",
    "is_show": 1,
    "service_name": "楽天カード"
  },
  {
    "id": 277,
    "point_id": 2,
    "title": "楽天プレミアムカード新規入会＆利用でポイント進呈",
    "period_text": null,
    "reward_rate_text": "新規入会＆利用で最大5,000ポイント、楽天市場でポイント3倍",
    "entry_required": 0,
    "target_stores": null,
    "detail_url": "https://www.rakuten-card.co.jp/campaign/premium_card/?l-id=corp_oo_new_cpnbr_pre_pc",
    "source_list_url": "https://www.rakuten-card.co.jp/campaign/?l-id=corp_oo_gnav_campaign_responsive",
    "is_show": 1,
    "service_name": "楽天カード"
  },
  {
    "id": 278,
    "point_id": 2,
    "title": "楽天ゴールドカード新規入会＆利用でポイント進呈",
    "period_text": null,
    "reward_rate_text": "5,000ポイント",
    "entry_required": 0,
    "target_stores": null,
    "detail_url": "https://www.rakuten-card.co.jp/campaign/gold_card/?l-id=corp_rc_corp_oo_new_cpnbr_gold_pc",
    "source_list_url": "https://www.rakuten-card.co.jp/campaign/?l-id=corp_oo_gnav_campaign_responsive",
    "is_show": 1,
    "service_name": "楽天カード"
  },
  {
    "id": 279,
    "point_id": 2,
    "title": "楽天ANAマイレージクラブカード新規入会＆利用でポイント進呈",
    "period_text": null,
    "reward_rate_text": "5,000ポイント",
    "entry_required": 0,
    "target_stores": null,
    "detail_url": "https://www.rakuten-card.co.jp/campaign/rakuten_amc_card/?l-id=corp_rc_cpnbr_list_ana",
    "source_list_url": "https://www.rakuten-card.co.jp/campaign/?l-id=corp_oo_gnav_campaign_responsive",
    "is_show": 1,
    "service_name": "楽天カード"
  },
  {
    "id": 280,
    "point_id": 2,
    "title": "初めてのキャッシングで最大2カ月間お利息全額キャッシュバック｜楽天カード",
    "period_text": "2025年5月1日～2026年5月31日",
    "reward_rate_text": "最大2カ月間お利息全額キャッシュバック",
    "entry_required": 1,
    "target_stores": null,
    "detail_url": "https://www.rakuten-card.co.jp/campaign/ca/ca_cashback?scid=wi_rkc_ca_corp_cpnlist_fullcb_new",
    "source_list_url": "https://www.rakuten-card.co.jp/campaign/?l-id=corp_oo_gnav_campaign_responsive",
    "is_show": 1,
    "service_name": "楽天カード"
  },
  {
    "id": 281,
    "point_id": 2,
    "title": "新規入会で本日のお買いものから使えるポイント進呈｜楽天カード",
    "period_text": null,
    "reward_rate_text": "最大6,000ポイント進呈、楽天市場でポイント3倍",
    "entry_required": 1,
    "target_stores": null,
    "detail_url": "https://www.rakuten-card.co.jp/campaign/rakuten_card/instant/payment/pay/bonus/?referrer=n-RSKa30&scid=wi_rkc_rc_corp_cpn_paybonus",
    "source_list_url": "https://www.rakuten-card.co.jp/campaign/?l-id=corp_oo_gnav_campaign_responsive",
    "is_show": 1,
    "service_name": "楽天カード"
  },
  {
    "id": 282,
    "point_id": 2,
    "title": "「自動でリボ払い」にご登録&ご利用で最大5,000ポイント！",
    "period_text": "常時開催",
    "reward_rate_text": "最大5,000ポイント（ご登録特典：2,000ポイント(5%)、500ポイント(15%)、100ポイント(80%)、ご利用特典：3,000ポイント）",
    "entry_required": 1,
    "target_stores": null,
    "detail_url": "https://www.rakuten-card.co.jp/campaign/revo/automatic/moushikomiriyou60000_maxpoint5000/",
    "source_list_url": "https://www.rakuten-card.co.jp/campaign/?l-id=corp_oo_gnav_campaign_responsive",
    "is_show": 1,
    "service_name": "楽天カード"
  },
  {
    "id": 283,
    "point_id": 2,
    "title": "5と0のつく日はエントリー＆楽天カードご利用でポイント+3倍でポイント4倍",
    "period_text": "毎月5、10、15、20、25、30日の00:00～23:59まで",
    "reward_rate_text": "ポイント4倍",
    "entry_required": 1,
    "target_stores": "楽天市場の全ショップ",
    "detail_url": "https://event.rakuten.co.jp/card/pointday/",
    "source_list_url": "https://www.rakuten-card.co.jp/campaign/?l-id=corp_oo_gnav_campaign_responsive",
    "is_show": 1,
    "service_name": "楽天カード"
  },
  {
    "id": 285,
    "point_id": 2,
    "title": "口座開設時に楽天銀行カードの入会と条件達成で最大8,000円相当もらえる！",
    "period_text": "楽天銀行口座新規開設・楽天銀行カード新規入会期間：2026年3月2日（月）10:00～2026年3月19日（木）09:59、楽天銀行口座入金期間：2026年3月2日（月）10:00～2026年4月30日（木）22:59",
    "reward_rate_text": "最大8,000円相当（入会特典2,000ポイント、カード利用特典3,000ポイント、楽天銀行口座への3万円以上の入金で3,000円）",
    "entry_required": 0,
    "target_stores": null,
    "detail_url": "https://www.rakuten-bank.co.jp/campaign/account/2603-C02/?scid=we_rbn_rc_202603corp_cpn",
    "source_list_url": "https://www.rakuten-card.co.jp/campaign/?l-id=corp_oo_gnav_campaign_responsive",
    "is_show": 1,
    "service_name": "楽天カード"
  },
  {
    "id": 286,
    "point_id": 2,
    "title": "2枚目の楽天カードを作成＆利用でポイント進呈",
    "period_text": "2026年3月13日(金)10:00～2026年4月30日(木)まで",
    "reward_rate_text": "500ポイント",
    "entry_required": 1,
    "target_stores": null,
    "detail_url": "https://www.rakuten-card.co.jp/campaign/add-card/?l-id=corp_rc_2ndcard_corp_koushin",
    "source_list_url": "https://www.rakuten-card.co.jp/campaign/?l-id=corp_oo_gnav_campaign_responsive",
    "is_show": 1,
    "service_name": "楽天カード"
  },
  {
    "id": 287,
    "point_id": 2,
    "title": "楽天カードを友達に紹介しよう！紹介するごとにポイント進呈｜楽天カード",
    "period_text": "常時開催",
    "reward_rate_text": "紹介する方に1,000ポイント、紹介された方に最大6,000ポイント",
    "entry_required": 0,
    "target_stores": null,
    "detail_url": "https://www.rakuten-card.co.jp/campaign/rakuten_card/susumail/?l-id=corp_oo_cpnbr_list_sus_pc_a",
    "source_list_url": "https://www.rakuten-card.co.jp/campaign/?l-id=corp_oo_gnav_campaign_responsive",
    "is_show": 1,
    "service_name": "楽天カード"
  },
  {
    "id": 288,
    "point_id": 2,
    "title": "楽天ゴールドカード 国内旅行を楽しむ方におすすめの1枚｜楽天カード",
    "period_text": "2026年2月27日(金)10:00～2026年3月31日(火)9:59",
    "reward_rate_text": "1,000ポイント",
    "entry_required": 1,
    "target_stores": null,
    "detail_url": "https://www.rakuten-card.co.jp/campaign/gold_card/hoyu/?l-id=corp_rc_corp_oo_cpnbr_list_gold_sw",
    "source_list_url": "https://www.rakuten-card.co.jp/campaign/?l-id=corp_oo_gnav_campaign_responsive",
    "is_show": 1,
    "service_name": "楽天カード"
  },
  {
    "id": 289,
    "point_id": 2,
    "title": "楽天プレミアムカード入会でポイント進呈",
    "period_text": "2026年2月27日(金)10:00～2026年3月31日(火)9:59",
    "reward_rate_text": "楽天市場のお買い物がポイント3倍",
    "entry_required": 1,
    "target_stores": "楽天市場",
    "detail_url": "https://www.rakuten-card.co.jp/campaign/premium_card/hoyu/?l-id=corp_rc_corp_oo_cpnbr_list_pre_sw",
    "source_list_url": "https://www.rakuten-card.co.jp/campaign/?l-id=corp_oo_gnav_campaign_responsive",
    "is_show": 1,
    "service_name": "楽天カード"
  },
  {
    "id": 290,
    "point_id": 2,
    "title": "家族カード作成＆利用でポイント進呈",
    "period_text": "毎月開催（エントリー期間：カードお申し込み月の1日0:00～月末23:59まで、家族カード発行日の翌月末までに利用）",
    "reward_rate_text": "500ポイント",
    "entry_required": 1,
    "target_stores": null,
    "detail_url": "https://www.rakuten-card.co.jp/campaign/rakuten_card/family/add/?l-id=corp_rc_cpnbr_list_family_pc_add",
    "source_list_url": "https://www.rakuten-card.co.jp/campaign/?l-id=corp_oo_gnav_campaign_responsive",
    "is_show": 1,
    "service_name": "楽天カード"
  },
  {
    "id": 291,
    "point_id": 2,
    "title": "【常時開催】分割払いまたはリボ払いのご利用で抽選で10,000ポイント！",
    "period_text": "カードご利用期間：2026年3月1日(日)0:00～2026年4月30日(木)23:59",
    "reward_rate_text": "抽選で10,000ポイント！",
    "entry_required": 1,
    "target_stores": null,
    "detail_url": "https://www.rakuten-card.co.jp/campaign/paymentsupport/",
    "source_list_url": "https://www.rakuten-card.co.jp/campaign/?l-id=corp_oo_gnav_campaign_responsive",
    "is_show": 1,
    "service_name": "楽天カード"
  },
  {
    "id": 292,
    "point_id": 2,
    "title": "【常時開催】楽天カード会員様へ 楽天モバイルお申し込みで3,000ポイントプレゼント",
    "period_text": "2023年5月8日（月）9:00～常時開催",
    "reward_rate_text": "3,000ポイント",
    "entry_required": 1,
    "target_stores": null,
    "detail_url": "https://ac.ebis.ne.jp/tr_set.php?argument=ZMhPE4GP&ai=rgp_mno_004075",
    "source_list_url": "https://www.rakuten-card.co.jp/campaign/?l-id=corp_oo_gnav_campaign_responsive",
    "is_show": 1,
    "service_name": "楽天カード"
  },
  {
    "id": 293,
    "point_id": 2,
    "title": "リーベイツ×楽天カード 楽天ポイントをお得にゲット",
    "period_text": null,
    "reward_rate_text": "初回購入特典：最大500ポイント進呈、獲得ポイントは購入金額(税抜)の20%を上限",
    "entry_required": 0,
    "target_stores": null,
    "detail_url": "https://www.rakuten-card.co.jp/point/rebates/",
    "source_list_url": "https://www.rakuten-card.co.jp/campaign/?l-id=corp_oo_gnav_campaign_responsive",
    "is_show": 1,
    "service_name": "楽天カード"
  },
  {
    "id": 294,
    "point_id": 2,
    "title": "初めてのキャッシングで最大2カ月間お利息全額キャッシュバック",
    "period_text": "常時開催",
    "reward_rate_text": "最大2カ月間お利息全額キャッシュバック",
    "entry_required": 1,
    "target_stores": null,
    "detail_url": "https://www.rakuten-card.co.jp/campaign/ca/ca_cashback?scid=wi_rkc_ca_corp_cpnlist_fullcb_exist",
    "source_list_url": "https://www.rakuten-card.co.jp/campaign/?l-id=corp_oo_gnav_campaign_responsive",
    "is_show": 1,
    "service_name": "楽天カード"
  },
  {
    "id": 295,
    "point_id": 2,
    "title": "キャッシング枠をご希望＆付帯で最大1,000ポイント！",
    "period_text": "常時開催",
    "reward_rate_text": "最大1,000ポイント",
    "entry_required": 1,
    "target_stores": null,
    "detail_url": "https://www.rakuten-card.co.jp/campaign/ca/ca2000/?l-id=corp_ca_campaignlist_include_existing",
    "source_list_url": "https://www.rakuten-card.co.jp/campaign/?l-id=corp_oo_gnav_campaign_responsive",
    "is_show": 1,
    "service_name": "楽天カード"
  },
  {
    "id": 296,
    "point_id": 2,
    "title": "JAFに新規ご入会のうえ、楽天カードでお支払いで1,000ポイント！",
    "period_text": "2026年1月30日(金)0:00～2026年3月31日(火)23:59",
    "reward_rate_text": "1,000ポイント",
    "entry_required": 1,
    "target_stores": "JAF",
    "detail_url": "https://www.rakuten-card.co.jp/campaign/xlo/20260130/",
    "source_list_url": "https://www.rakuten-card.co.jp/campaign/?l-id=corp_oo_gnav_campaign_responsive",
    "is_show": 1,
    "service_name": "楽天カード"
  },
  {
    "id": 297,
    "point_id": 2,
    "title": "【ポイプラジャンボ】抽選で最大10,000ポイント！エントリーだけでももれなく1ポイント！",
    "period_text": "2026年2月27日(金)0:00～2026年3月31日(火)23:59",
    "reward_rate_text": "抽選で最大10,000ポイント、エントリーだけでもれなく1ポイント",
    "entry_required": 1,
    "target_stores": null,
    "detail_url": "https://www.rakuten-card.co.jp/campaign/xlo/jumbo/?l-id=corp_oo_cpnll_corp_jumbo",
    "source_list_url": "https://www.rakuten-card.co.jp/campaign/?l-id=corp_oo_gnav_campaign_responsive",
    "is_show": 1,
    "service_name": "楽天カード"
  },
  {
    "id": 298,
    "point_id": 2,
    "title": "セブン‐イレブンご利用で抽選で500名様に10,000ポイント",
    "period_text": "エントリー期間：2026年2月27日(金)10:00～2026年3月31日(火)23:59、ご利用期間：2026年3月1日(日)0:00～2026年3月31日(火)23:59",
    "reward_rate_text": "抽選で500名様に10,000ポイント",
    "entry_required": 1,
    "target_stores": "セブン‐イレブン",
    "detail_url": "https://www.rakuten-card.co.jp/campaign/xlo/20260227/",
    "source_list_url": "https://www.rakuten-card.co.jp/campaign/?l-id=corp_oo_gnav_campaign_responsive",
    "is_show": 1,
    "service_name": "楽天カード"
  },
  {
    "id": 299,
    "point_id": 2,
    "title": "【2,000ポイントGET】口座開設キャンペーン | 楽天証券",
    "period_text": null,
    "reward_rate_text": "2,000ポイント",
    "entry_required": 1,
    "target_stores": null,
    "detail_url": "https://r10.to/hN7rLj",
    "source_list_url": "https://www.rakuten-card.co.jp/campaign/?l-id=corp_oo_gnav_campaign_responsive",
    "is_show": 1,
    "service_name": "楽天カード"
  },
  {
    "id": 300,
    "point_id": 2,
    "title": "楽天カード会員様限定！エントリー 楽天でんき お申し込み ご利用で8,000ポイント進呈！",
    "period_text": "2026年3月2日(月)10:00 〜 2026年4月2日(木)9:59",
    "reward_rate_text": "楽天でんき加入特典ポイント 11,000ポイント獲得",
    "entry_required": 1,
    "target_stores": null,
    "detail_url": "https://r10.to/hk2XUa",
    "source_list_url": "https://www.rakuten-card.co.jp/campaign/?l-id=corp_oo_gnav_campaign_responsive",
    "is_show": 1,
    "service_name": "楽天カード"
  },
  {
    "id": 301,
    "point_id": 3,
    "title": "セブンカード・プラス新規ご入会キャンペーン！",
    "period_text": "2025年11月1日（土）〜",
    "reward_rate_text": "最大9,000nanacoポイントプレゼント！",
    "entry_required": 0,
    "target_stores": null,
    "detail_url": "https://www.7card.co.jp/campaign/index.html",
    "source_list_url": "https://www.7card.co.jp/campaign/index.html#campaign",
    "is_show": 1,
    "service_name": "セブンプラスカード"
  },
  {
    "id": 302,
    "point_id": 4,
    "title": "ベイシア・ベイシア電器×au PAYキャンペーン",
    "period_text": "2026年3月2日（月）～3月31日（火）",
    "reward_rate_text": "抽選で最大10,000Pontaポイント、500円割引きクーポン",
    "entry_required": 1,
    "target_stores": "ベイシア、ベイシア電器の各対象店舗",
    "detail_url": "https://camp.auone.jp/campaign/7cb1921c7fd260245f62044a?utm_source=aupaycode&utm_medium=web&utm_campaign=cpnlist",
    "source_list_url": "https://aupay.wallet.auone.jp/campaign/",
    "is_show": 1,
    "service_name": "au Pay"
  },
  {
    "id": 303,
    "point_id": 4,
    "title": "ニトリネット × au PAY",
    "period_text": "2026年3月1日(日)～3月17日(火)",
    "reward_rate_text": "最大10％還元（還元上限は1au IDあたり2,000ポイント/回・期間）",
    "entry_required": 0,
    "target_stores": "ニトリネット",
    "detail_url": "https://media.aupay.wallet.auone.jp/lp/campaign/202603_nitori?utm_source=aupaycode&utm_medium=web&utm_campaign=cpnlist",
    "source_list_url": "https://aupay.wallet.auone.jp/campaign/",
    "is_show": 1,
    "service_name": "au Pay"
  },
  {
    "id": 304,
    "point_id": 4,
    "title": "京樽 × au PAY キャンペーン",
    "period_text": "2026年3月4日〜2026年4月11日",
    "reward_rate_text": "最大10%（20ポイント/200円）還元、上限500ポイント/期間",
    "entry_required": 1,
    "target_stores": "京樽テイクアウトWeb予約",
    "detail_url": "https://aupay-cp.auone.jp/202603_kyotaru?utm_source=aupaycode&utm_medium=web&utm_campaign=cpnlist",
    "source_list_url": "https://aupay.wallet.auone.jp/campaign/",
    "is_show": 1,
    "service_name": "au Pay"
  },
  {
    "id": 305,
    "point_id": 4,
    "title": "ビックカメラ池袋店 × au PAYキャンペーン",
    "period_text": "2026年3月14日（土）～3月29日（日）",
    "reward_rate_text": "最大5%割引クーポン",
    "entry_required": 1,
    "target_stores": "ビックカメラ 池袋本店, ビックカメラ 池袋西口 IT tower TOKYO店, ビックカメラ 池袋西口店, ビックカメラ 池袋カメラ・パソコン館, ビック酒販 池袋東口店",
    "detail_url": "https://aupay-cp.auone.jp/202603_biccamera?utm_source=aupaycode&utm_medium=web&utm_campaign=cpnlist",
    "source_list_url": "https://aupay.wallet.auone.jp/campaign/",
    "is_show": 1,
    "service_name": "au Pay"
  },
  {
    "id": 306,
    "point_id": 4,
    "title": "ジハンピ × au PAY | キャンペーン",
    "period_text": "2026年3月1日（日）～ 3月31日（火）",
    "reward_rate_text": "最大150円相当をau PAY 残高に還元",
    "entry_required": 0,
    "target_stores": "ジハンピ",
    "detail_url": "https://media.aupay.wallet.auone.jp/lp/campaign/202603_jihampi?utm_source=aupaycode&utm_medium=web&utm_campaign=cpnlist",
    "source_list_url": "https://aupay.wallet.auone.jp/campaign/",
    "is_show": 1,
    "service_name": "au Pay"
  },
  {
    "id": 307,
    "point_id": 4,
    "title": "はるやま × au PAY",
    "period_text": "2026年3月9日(月) ～ 2026年3月31日(火)",
    "reward_rate_text": "最大10％（20ポイント/200円）還元（上限1au IDあたり1,000ポイント/回・期間）",
    "entry_required": 0,
    "target_stores": "はるやま",
    "detail_url": "https://aupay-cp.auone.jp/202603_haruyama?utm_source=aupaycode&utm_medium=web&utm_campaign=cpnlist",
    "source_list_url": "https://aupay.wallet.auone.jp/campaign/",
    "is_show": 1,
    "service_name": "au Pay"
  },
  {
    "id": 308,
    "point_id": 4,
    "title": "ケーズデンキ × au PAY キャンペーン",
    "period_text": "2026年3月13日（金）～3月16日（月）",
    "reward_rate_text": "1,000円割引クーポン",
    "entry_required": 1,
    "target_stores": "ケーズデンキ",
    "detail_url": "https://aupay-cp.auone.jp/202603_ksdenki_storelimited?utm_source=aupaycode&utm_medium=web&utm_campaign=cpnlist",
    "source_list_url": "https://aupay.wallet.auone.jp/campaign/",
    "is_show": 1,
    "service_name": "au Pay"
  },
  {
    "id": 309,
    "point_id": 4,
    "title": "キャッシュレスで購入すると今ならスタンプ2倍！",
    "period_text": "2026年4月30日(木)まで",
    "reward_rate_text": "スタンプ2倍",
    "entry_required": 0,
    "target_stores": "対象自販機",
    "detail_url": "https://c.cocacola.co.jp/spn/app/cp/20260301_cashlesswstamp/index.html?utm_source=otherdigital_p&utm_medium=Other&utm_campaign=202603_cashlesswstamp&utm_term=aupay_264_264&utm_content=link",
    "source_list_url": "https://aupay.wallet.auone.jp/campaign/",
    "is_show": 1,
    "service_name": "au Pay"
  },
  {
    "id": 310,
    "point_id": 4,
    "title": "ワイプラザ輪島 × 出張輪島朝市 × au PAY",
    "period_text": "2025年12月1日（月）～ 2026年3月31日（火）",
    "reward_rate_text": "2,000Pontaポイント",
    "entry_required": 0,
    "target_stores": "ワイプラザ輪島、出張輪島朝市",
    "detail_url": "https://media.aupay.wallet.auone.jp/lp/campaign/202512_waiplaza_wajima-s?utm_source=aupaycode&utm_medium=web&utm_campaign=cpnlist",
    "source_list_url": "https://aupay.wallet.auone.jp/campaign/",
    "is_show": 1,
    "service_name": "au Pay"
  },
  {
    "id": 311,
    "point_id": 4,
    "title": "カラオケ館 × au PAYキャンペーン",
    "period_text": "2026年3月1日（日）～3月31日（火）",
    "reward_rate_text": "最大10%割引クーポン（割引上限は、500円/回）",
    "entry_required": 1,
    "target_stores": "カラオケ館全店",
    "detail_url": "https://aupay-cp.auone.jp/202603_karaokekan?utm_source=aupaycode&utm_medium=web&utm_campaign=cpnlist",
    "source_list_url": "https://aupay.wallet.auone.jp/campaign/",
    "is_show": 1,
    "service_name": "au Pay"
  },
  {
    "id": 312,
    "point_id": 4,
    "title": "ホクレンSS × au PAY",
    "period_text": "2026年2月13日（金） 〜 3月15日（日）",
    "reward_rate_text": "抽選で合計1,540名様に最大10,000円相当（不課税）au PAY 残高還元！ 1等：10,000円相当（不課税）× 40名様、2等：1,000円相当（不課税）× 500名様、3等：100円相当（不課税）× 1,000名様",
    "entry_required": 0,
    "target_stores": "ホクレンSS",
    "detail_url": "https://aupay-cp.auone.jp/202602_hokuren?utm_source=aupaycode&utm_medium=web&utm_campaign=cpnlist",
    "source_list_url": "https://aupay.wallet.auone.jp/campaign/",
    "is_show": 1,
    "service_name": "au Pay"
  },
  {
    "id": 313,
    "point_id": 4,
    "title": "淡路サービスエリア × au PAY",
    "period_text": "2026年2月13日（金）〜2026年3月15日（日）",
    "reward_rate_text": "Pontaポイント最大20%還元（片方のみ最大10%還元）、還元上限500ポイント/回、2,000ポイント/期間",
    "entry_required": 1,
    "target_stores": "淡路サービスエリア 上り線（売店、レストランROYAL、外売店、Café a too）、淡路サービスエリア 下り線（売店、レストランROYAL、外売店、ミスタードーナツ、スターバックスコーヒー） ※淡路ハイウェイオアシスは対象外",
    "detail_url": "https://aupay-cp.auone.jp/202602_awaji-rs?utm_source=aupaycode&utm_medium=web&utm_campaign=cpnlist",
    "source_list_url": "https://aupay.wallet.auone.jp/campaign/",
    "is_show": 1,
    "service_name": "au Pay"
  },
  {
    "id": 314,
    "point_id": 4,
    "title": "［3月］au × Ponta グリーンライフポイント",
    "period_text": "2026年3月1日0:00〜2026年3月31日23:59",
    "reward_rate_text": "200円につき1Pontaポイント",
    "entry_required": 1,
    "target_stores": "アークスグループ, 居酒屋 一休, ISHIYA, ViTO×IWAIZUMI, Aコープ 伊達, エコス, S-mart",
    "detail_url": "https://camp.auone.jp/campaign/b6405f2d20a4e6e80a8a3e34?utm_source=aupay&utm_medium=web&utm_campaign=cpnlist_20230110_20230331",
    "source_list_url": "https://aupay.wallet.auone.jp/campaign/",
    "is_show": 1,
    "service_name": "au Pay"
  },
  {
    "id": 321,
    "point_id": 1,
    "title": "超PayPay祭X（Twitter）キャンペーン",
    "period_text": "2026年3月13日（金）〜2026年3月20日（金）23:59",
    "reward_rate_text": "抽選で1万ポイントを10名様にプレゼント",
    "entry_required": 1,
    "target_stores": null,
    "detail_url": "https://paypay.ne.jp/event/xcp-paypay-matsuri-20260226/",
    "source_list_url": "https://paypay.ne.jp/event/",
    "is_show": 1,
    "service_name": "PayPay"
  },
  {
    "id": 334,
    "point_id": 5,
    "title": "Olive × SMBC レディスゴルフトーナメント開催記念キャンペーン",
    "period_text": "2026年3月9日(月) 〜 2026年3月31日(火)",
    "reward_rate_text": "プロゴルファーのサイン色紙をプレゼント (抽選60名)",
    "entry_required": 1,
    "target_stores": null,
    "detail_url": "https://www.smbc.co.jp/kojin/olive/special/campaign/collab/vpoint-ladies202603/?link_id=CP04675_i_webTCP_CT52561_img&utm_source=web&utm_medium=TCP&utm_campaign=CP04675_i_webTCP_CT52561_img",
    "source_list_url": "https://www.smbc.co.jp/kojin/campaign/",
    "is_show": 1,
    "service_name": "Oliveカード"
  },
  {
    "id": 342,
    "point_id": 5,
    "title": "Olive(オリーブ)の口座残高を増やすほどVポイントが貯まる！ 三井住友銀行",
    "period_text": null,
    "reward_rate_text": "円預金残高に応じてVポイント還元率が最大+3%アップ、毎月最大1,100pt貯まる。さらに、初めてOliveで給与を受け取ると1年間でVポイント3,400pt。",
    "entry_required": 0,
    "target_stores": "セコマ、セイコーマート、セブン-イレブン、ポプラ、ミニストップ、ローソン、マクドナルド、モスバーガー、ケンタッキーフライドチキン、餃子の王将、サイゼリヤ、ガスト、バーミヤン、しゃぶ葉、ジョナサン、夢庵、その他すかいらーくグループ飲食店舗、すき家、はま寿司、ココス、スターバックス、ドトールコーヒーショップ、エクセルシオールカフェ、かっぱ寿司",
    "detail_url": "https://www.smbc.co.jp/kojin/vpoint-up/yokin/?aff=CP04605_i_webOTH_CT49495_img&utm_source=web&utm_medium=OTH&utm_campaign=CP04605_i_webOTH_CT49495_img",
    "source_list_url": "https://www.smbc.co.jp/kojin/campaign/",
    "is_show": 1,
    "service_name": "Oliveカード"
  },
  {
    "id": 347,
    "point_id": 5,
    "title": "Olive限定！外貨クレカ積立キャンペーン実施中！",
    "period_text": "2026/1/19(月) ` 2026/4/17(金) 23:59",
    "reward_rate_text": "ポイント還元（最大3%）",
    "entry_required": 1,
    "target_stores": null,
    "detail_url": "https://www.smbc.co.jp/kojin/olive/special/campaign/gaika/tsumitate2601?link_id=CP04295_i_webOTH_CT48328_img&utm_source=web&utm_medium=OTH&utm_campaign=CP04295_i_webOTH_CT48328_img",
    "source_list_url": "https://www.smbc.co.jp/kojin/campaign/",
    "is_show": 1,
    "service_name": "Oliveカード"
  },
  {
    "id": 348,
    "point_id": 5,
    "title": "Vサービスリリース記念 外貨ダブルキャンペーン",
    "period_text": "外貨預金口座開設キャンペーン：2026/1/19(月)〜2026/4/17(金) 23:59、外貨クレカ積立キャンペーン：エントリー期間 2026/1/19(月)〜2026/4/17(金) 23:59、積立判定期間 2026/3/26(水)〜2026/11/26(水) 23:59",
    "reward_rate_text": "外貨預金口座開設キャンペーン：Vポイント3,000円相当、外貨クレカ積立キャンペーン：Vポイント3,000円相当",
    "entry_required": 1,
    "target_stores": null,
    "detail_url": "https://www.smbc.co.jp/kojin/olive/special/campaign/gaika/matome2601?link_id=CP04293_i_webOTH_CT48379_img&utm_source=web&utm_medium=OTH&utm_campaign=CP04293_i_webOTH_CT48379_img",
    "source_list_url": "https://www.smbc.co.jp/kojin/campaign/",
    "is_show": 1,
    "service_name": "Oliveカード"
  },
  {
    "id": 388,
    "point_id": 4,
    "title": "au PAY Pontaアップ店",
    "period_text": null,
    "reward_rate_text": "Pontaポイントがさらにたまる",
    "entry_required": 0,
    "target_stores": null,
    "detail_url": "https://aupay.auone.jp/contents/lp/pontaup/index.html?utm_source=aupaycode&utm_medium=web&utm_campaign=cpnlist_20240229_20991231",
    "source_list_url": "https://aupay.wallet.auone.jp/campaign/",
    "is_show": 1,
    "service_name": "au Pay"
  }
]